.DS_Store
network_analyzer/__init__.py
network_analyzer/logger.conf
network_analyzer-0.0.2.5.dist-info/METADATA
network_analyzer-0.0.2.5.dist-info/RECORD
network_analyzer-0.0.2.5.dist-info/WHEEL
network_analyzer-0.0.2.5.dist-info/top_level.txt
rpc_apiserver/__init__.py
rpc_apiserver/__main__.py
rpc_apiserver/logger.conf
rpc_apiserver/server.py
socketio_server/__init__.py
socketio_server/__main__.py
socketio_server/logger.conf
socketio_server/server.py
