Metadata-Version: 2.1
Name: network-analyzer
Version: 0.0.2.5
Summary: Analyze your network traffic with ease
Home-page: https://github.com/ashutoshdtu/network-analyzer
Author: Ashutosh Mishra
Author-email: ashutoshdtu@gmail.com
Maintainer: Saurabh Shandilya
Maintainer-email: saurabhshandilya.1991@gmail.com
License: GPL-2.0
Platform: UNKNOWN
Classifier: Development Status :: 2 - Pre-Alpha
Classifier: Framework :: Flask
Classifier: License :: OSI Approved :: GNU General Public License v2 (GPLv2)
Classifier: Programming Language :: Python :: 2.7
Classifier: Operating System :: POSIX
Classifier: Topic :: System :: Monitoring
Classifier: Topic :: System :: Networking
Requires-Dist: Flask (==1.0.2)
Requires-Dist: python-socketio (==2.0.0)
Requires-Dist: flask-socketio (==3.0.1)
Requires-Dist: jsonrpcserver (==3.5.6)
Requires-Dist: gunicorn (==19.9.0)
